README.txt
setup.py
torent/__init__.py
torent/client.py
torent/comunicator.py
torrent.egg-info/PKG-INFO
torrent.egg-info/SOURCES.txt
torrent.egg-info/dependency_links.txt
torrent.egg-info/requires.txt
torrent.egg-info/top_level.txt