Metadata-Version: 1.1
Name: torrent
Version: 0
Summary: python data scharing
Home-page: https://github.com/JulianWww/torent
Author: Julian Wandhoven
Author-email: julian.wandhoven@fgz.ch
License: wtfpl
Download-URL: https://github.com/JulianWww/torent/archive/0.tar.gz
Keywords: data,multicomputer,userfriendly,simple
Platform: UNKNOWN
Classifier: Development Status :: 3 - Alpha
Classifier: Intended Audience :: Developers
Classifier: Topic :: Internet :: Proxy Servers
Classifier: License :: OSI Approved :: MIT License
Classifier: Programming Language :: Python :: 3.6
Classifier: Programming Language :: Python :: 3
